magicdb_cli/__init__.py
magicdb_cli/bucket_util.py
magicdb_cli/magicdbEtcdClient.py
magicdb_cli/magicdbLexer.py
magicdb_cli/magicdbListenerHandler.py
magicdb_cli/magicdbLoad.py
magicdb_cli/magicdbLoadSpark.py
magicdb_cli/magicdbParser.py
magicdb_cli/magicdbParserListener.py
magicdb_cli/magicdbcli.py
magicdb_cli-1.0.23.dist-info/LICENSE
magicdb_cli-1.0.23.dist-info/METADATA
magicdb_cli-1.0.23.dist-info/WHEEL
magicdb_cli-1.0.23.dist-info/entry_points.txt
magicdb_cli-1.0.23.dist-info/top_level.txt
magicdb_cli-1.0.23.dist-info/RECORD
