Metadata-Version: 2.1
Name: magicdb-cli
Version: 1.0.23
Summary: magicdb client cmd tool
Home-page: https://github.com/uopensail/magicdb-cli
Author: TimePi
Author-email: timepi@uopensail.com
License: License :: AGLP3
Keywords: magicdb client
Platform: any
Classifier: Development Status :: 5 - Production/Stable
Classifier: Intended Audience :: Developers
Classifier: License :: OSI Approved :: GNU Affero General Public License v3
Classifier: Programming Language :: Python :: 3
Classifier: Programming Language :: Python :: 3.7
Classifier: Programming Language :: Python :: 3.8
Classifier: Programming Language :: Python :: 3.9
Classifier: Programming Language :: Python :: 3.10
Classifier: Topic :: Software Development :: Libraries
Classifier: Topic :: Utilities
Requires-Python: >=3.7
License-File: LICENSE
Requires-Dist: mmh3 ==3.0.0
Requires-Dist: pandas ==1.2.0
Requires-Dist: pyarrow ==6.0.1
Requires-Dist: antlr4-python3-runtime ==4.12
Requires-Dist: etcd3 ==0.12.0
Requires-Dist: awswrangler ==2.18.0
Requires-Dist: boto3 ==1.26.27
